gofile_dl/__init__.py
gofile_dl/gofile_dl.py
gofile_dl-1.2.2.dist-info/LICENSE
gofile_dl-1.2.2.dist-info/METADATA
gofile_dl-1.2.2.dist-info/WHEEL
gofile_dl-1.2.2.dist-info/entry_points.txt
gofile_dl-1.2.2.dist-info/top_level.txt
gofile_dl-1.2.2.dist-info/RECORD
