Metadata-Version: 2.1
Name: gofile-dl
Version: 1.2.2
Summary: Download files from gofile.io
Home-page: https://github.com/rdnkarchiver/gofile-dl
Author: rdnkarchiver
Author-email: rdnkarchiver@protonmail.com
License: UNKNOWN
Project-URL: Bug Tracker, https://github.com/rdnkarchiver/gofile-dl/issues
Platform: UNKNOWN
Classifier: Programming Language :: Python :: 3
Classifier: License :: OSI Approved :: Apache Software License
Classifier: Operating System :: OS Independent
Requires-Python: >=3.6
License-File: LICENSE
Requires-Dist: aiohttp
Requires-Dist: gofile-client
Requires-Dist: tqdm
